weheat_backend_client/__init__.py
weheat_backend_client/api_client.py
weheat_backend_client/api_response.py
weheat_backend_client/configuration.py
weheat_backend_client/exceptions.py
weheat_backend_client/py.typed
weheat_backend_client/rest.py
weheat_backend_client/abstractions/__init__.py
weheat_backend_client/abstractions/auth.py
weheat_backend_client/abstractions/discovery.py
weheat_backend_client/abstractions/heat_pump.py
weheat_backend_client/api/__init__.py
weheat_backend_client/api/energy_log_api.py
weheat_backend_client/api/heat_pump_api.py
weheat_backend_client/api/heat_pump_log_api.py
weheat_backend_client/models/__init__.py
weheat_backend_client/models/boiler_type.py
weheat_backend_client/models/device_state.py
weheat_backend_client/models/dhw_type.py
weheat_backend_client/models/energy_view_dto.py
weheat_backend_client/models/heat_pump_log_view_dto.py
weheat_backend_client/models/heat_pump_model.py
weheat_backend_client/models/heat_pump_status_enum.py
weheat_backend_client/models/heat_pump_type.py
weheat_backend_client/models/raw_heat_pump_log_dto.py
weheat_backend_client/models/read_all_heat_pump_dto.py
weheat_backend_client/models/read_heat_pump_dto.py
weheat_backend_client-2024.6.19rc3.dist-info/METADATA
weheat_backend_client-2024.6.19rc3.dist-info/WHEEL
weheat_backend_client-2024.6.19rc3.dist-info/top_level.txt
weheat_backend_client-2024.6.19rc3.dist-info/RECORD
