Metadata-Version: 2.1
Name: weheat_backend_client
Version: 2024.6.19rc3
Summary: Weheat Backend client
Home-page: https://github.com/wefabricate/wh-public-backend-client
Author: Jesper Raemaekers
Author-email: jesper.raemaekers@wefabricate.com
Keywords: OpenAPI,OpenAPI-Generator,Weheat Backend
Requires-Dist: urllib3 <2.1.0,>=1.25.3
Requires-Dist: python-dateutil
Requires-Dist: pydantic >=2
Requires-Dist: typing-extensions >=4.7.1
Requires-Dist: aiohttp >=3.9.5
